[
  {
    "time": "13 November 2025 - 09:36 AM",
    "magnitude": "1.9",
    "location": "020km S 03° E of General Luna (Surigao Del Norte)"
  },
  {
    "time": "13 November 2025 - 08:19 AM",
    "magnitude": "2.2",
    "location": "010km S 13° W of City Of Bogo (Cebu)"
  },
  {
    "time": "13 November 2025 - 06:20 AM",
    "magnitude": "2.3",
    "location": "003km N 78° W of Mansalay (Oriental Mindoro)"
  },
  {
    "time": "13 November 2025 - 06:17 AM",
    "magnitude": "2.5",
    "location": "010km S 25° W of City Of Bogo (Cebu)"
  },
  {
    "time": "13 November 2025 - 06:09 AM",
    "magnitude": "2.3",
    "location": "008km S 26° E of City Of Bogo (Cebu)"
  },
  {
    "time": "13 November 2025 - 05:08 AM",
    "magnitude": "2.1",
    "location": "011km S 82° W of Socorro (Oriental Mindoro)"
  },
  {
    "time": "13 November 2025 - 04:49 AM",
    "magnitude": "2.1",
    "location": "022km N 61° E of City Of Bogo (Cebu)"
  },
  {
    "time": "13 November 2025 - 04:36 AM",
    "magnitude": "2.0",
    "location": "004km N 73° E of San Francisco (Southern Leyte)"
  },
  {
    "time": "13 November 2025 - 04:31 AM",
    "magnitude": "3.2",
    "location": "006km N 49° W of City Of Bogo (Cebu)"
  },
  {
    "time": "13 November 2025 - 04:27 AM",
    "magnitude": "2.2",
    "location": "016km N 68° E of Kabugao (Apayao)"
  }
]