[
  {
    "time": "15 November 2025 - 09:22 AM",
    "magnitude": "1.9",
    "location": "039km S 71° E of Marihatag (Surigao Del Sur)"
  },
  {
    "time": "15 November 2025 - 09:05 AM",
    "magnitude": "2.1",
    "location": "001km N 21° E of City Of Alaminos (Pangasinan)"
  },
  {
    "time": "15 November 2025 - 08:22 AM",
    "magnitude": "3.2",
    "location": "009km S 04° E of San Isidro (Davao Oriental)"
  },
  {
    "time": "15 November 2025 - 08:03 AM",
    "magnitude": "2.7",
    "location": "010km S 01° E of City Of Bogo (Cebu)"
  },
  {
    "time": "15 November 2025 - 07:23 AM",
    "magnitude": "3.2",
    "location": "023km S 11° E of Candoni (Negros Occidental)"
  },
  {
    "time": "15 November 2025 - 06:05 AM",
    "magnitude": "2.3",
    "location": "022km S 28° W of Cateel (Davao Oriental)"
  },
  {
    "time": "15 November 2025 - 05:48 AM",
    "magnitude": "1.9",
    "location": "009km N 42° E of City Of Bogo (Cebu)"
  },
  {
    "time": "15 November 2025 - 05:10 AM",
    "magnitude": "2.4",
    "location": "010km S 08° E of Bagac (Bataan)"
  },
  {
    "time": "15 November 2025 - 05:04 AM",
    "magnitude": "1.9",
    "location": "013km S 77° E of City Of Bogo (Cebu)"
  },
  {
    "time": "15 November 2025 - 04:51 AM",
    "magnitude": "2.0",
    "location": "009km S 30° W of City Of Bogo (Cebu)"
  }
]